
[
  {
    "title": "Vocabulary Chapter 1: Expectations",
    "full_description": "Flashcards for Chapter 1: Expectations. Click on a card to see the translation.",
    "tags": {
      "main_category": "Skills",
      "sub_category": ["Bygg & Anleggsfag"],
      "cefr_level": ["A2", "B1", "B2"],
      "group_size": ["Individual", "Pairs"],
      "preparation_required": "No Preparation (On-the-spot)",
      "materials_resources": ["Digital Device"],
      "sensitivity_warning": false,
      "activity_type": ["Vocabulary Building", "Self-study", "Flashcards"],
      "classroom_community_bonding": false,
      "thematically_adaptable": false,
      "teacher_instruction": "This chapter introduces foundational concepts. Encourage students to relate the Vg1/Vg2/Vg3 terms to their own educational paths if applicable. Ensure pronunciation practice for terms like 'journeyman's certificate'.",
      "flashcards": [
        { "term": "achieve", "definition": "oppnå" },
        { "term": "advanced course (Vg3)", "definition": "studieforberedende Vg3" },
        { "term": "apprentice", "definition": "lærling" },
        { "term": "apprenticeship", "definition": "læretid" },
        { "term": "assess", "definition": "vurdere" },
        { "term": "attend", "definition": "delta på, gå på" },
        { "term": "banging", "definition": "bankende, dundrende" },
        { "term": "bricklaying", "definition": "muring" },
        { "term": "building furnishings", "definition": "bygningsinnredning" },
        { "term": "building site", "definition": "byggeplass" },
        { "term": "capture", "definition": "fange, fange oppmerksomhet" },
        { "term": "champion", "definition": "mester" },
        { "term": "clogged", "definition": "tilstoppet" },
        { "term": "communication", "definition": "kommunikasjon" },
        { "term": "compare", "definition": "sammenligne" },
        { "term": "concrete", "definition": "betong" },
        { "term": "conquer", "definition": "erobre" },
        { "term": "considerable", "definition": "betydelig" },
        { "term": "conventional", "definition": "konvensjonell, tradisjonell" },
        { "term": "corporation", "definition": "selskap, konsern" },
        { "term": "current", "definition": "aktuell, nåværende" },
        { "term": "cyclone", "definition": "syklon" },
        { "term": "debt", "definition": "gjeld" },
        { "term": "demanding", "definition": "krevende" },
        { "term": "dictionary entry", "definition": "ordbokoppføring" },
        { "term": "discovery", "definition": "oppdagelse" },
        { "term": "employee", "definition": "ansatt" },
        { "term": "establish", "definition": "etablere" },
        { "term": "experience", "definition": "erfaring" },
        { "term": "factory", "definition": "fabrikk" },
        { "term": "fibreglass", "definition": "glassfiber" },
        { "term": "found (v)", "definition": "grunnlegge" },
        { "term": "foundation course (Vg1)", "definition": "grunnkurs Vg1" },
        { "term": "frustration", "definition": "frustrasjon" },
        { "term": "further", "definition": "videre" },
        { "term": "furniture", "definition": "møbler" },
        { "term": "hall of fame", "definition": "æresgalleri" },
        { "term": "haul", "definition": "slepe, frakte" },
        { "term": "HSE (Health, Safety & Environment)", "definition": "HMS - Helse, Miljø og Sikkerhet" },
        { "term": "impact", "definition": "innvirkning, påvirkning" },
        { "term": "industrial", "definition": "industriell" },
        { "term": "industrial plumber", "definition": "industrirørlegger" },
        { "term": "instruction manual", "definition": "bruksanvisning" },
        { "term": "intermediate course (Vg2)", "definition": "videregående kurs Vg2" },
        { "term": "invention", "definition": "oppfinnelse" },
        { "term": "invade", "definition": "invadere" },
        { "term": "issue", "definition": "sak, problem" },
        { "term": "job shadowing", "definition": "hospitering" },
        { "term": "journeyman's certificate", "definition": "svennebrev" },
        { "term": "knowledge", "definition": "kunnskap" },
        { "term": "land (v)", "definition": "lande" },
        { "term": "landscaper", "definition": "anleggsgartner" },
        { "term": "launch (v)", "definition": "lansere" },
        { "term": "licence (v)", "definition": "lisensiere" },
        { "term": "maintenance", "definition": "vedlikehold" },
        { "term": "miner", "definition": "gruvearbeider" },
        { "term": "motivating", "definition": "motiverende" },
        { "term": "moulded", "definition": "støpt" },
        { "term": "noun", "definition": "substantiv" },
        { "term": "Old Norse", "definition": "norrønt" },
        { "term": "option", "definition": "valg, alternativ" },
        { "term": "outdoors", "definition": "utendørs" },
        { "term": "pace", "definition": "tempo" },
        { "term": "painter/decorator", "definition": "maler/dekoratør" },
        { "term": "patent (v)", "definition": "patentere" },
        { "term": "patio", "definition": "terrasse, uteplass" },
        { "term": "pave", "definition": "belegge, asfaltere" },
        { "term": "physically", "definition": "fysisk" },
        { "term": "politician", "definition": "politiker" },
        { "term": "preacher", "definition": "predikant" },
        { "term": "profession", "definition": "yrke" },
        { "term": "progress", "definition": "fremgang" },
        { "term": "pronounce", "definition": "uttale" },
        { "term": "prototype", "definition": "prototyp" },
        { "term": "puncture", "definition": "punktering" },
        { "term": "qualified", "definition": "kvalifisert" },
        { "term": "quote", "definition": "sitat" },
        { "term": "restoration", "definition": "restaurering" },
        { "term": "sawmill", "definition": "sagbruk" },
        { "term": "scaffold", "definition": "stillas" },
        { "term": "source", "definition": "kilde" },
        { "term": "spin", "definition": "spinne, snurre" },
        { "term": "suited", "definition": "egnet" },
        { "term": "suction", "definition": "sug, sugekraft" },
        { "term": "supervisor", "definition": "veileder, overordnet" },
        { "term": "temporary", "definition": "midlertidig" },
        { "term": "term", "definition": "begrep" },
        { "term": "topic", "definition": "emne" },
        { "term": "trade", "definition": "fag, yrke" },
        { "term": "trade certificate", "definition": "fagbrev" },
        { "term": "tribe", "definition": "stamme" },
        { "term": "truth seekers", "definition": "sannhetssøkere" },
        { "term": "turf", "definition": "gressmatte, torv" },
        { "term": "unique", "definition": "unik" },
        { "term": "upgrade", "definition": "oppgradere" },
        { "term": "upper secondary school education programme", "definition": "videregående utdanningsprogram" },
        { "term": "vacuum cleaner", "definition": "støvsuger" },
        { "term": "vocational", "definition": "yrkesfaglig" },
        { "term": "vocational occupation", "definition": "yrke" },
        { "term": "vocabulary", "definition": "ordforråd" },
        { "term": "water supply", "definition": "vannforsyning" },
        { "term": "wheelbarrow", "definition": "trillebår" },
        { "term": "wood panelling", "definition": "trepanel" },
        { "term": "woodworking", "definition": "trearbeid" }
      ]
    }
  },
  {
    "title": "Vocabulary Chapter 2: Safe and Sound",
    "full_description": "Flashcards for Chapter 2: Safe and Sound. Click on a card to see the translation.",
    "tags": {
      "main_category": "Skills",
      "sub_category": ["Bygg & Anleggsfag"],
      "cefr_level": ["A2", "B1", "B2"],
      "group_size": ["Individual", "Pairs"],
      "preparation_required": "No Preparation (On-the-spot)",
      "materials_resources": ["Digital Device"],
      "sensitivity_warning": false,
      "activity_type": ["Vocabulary Building", "Self-study", "Flashcards"],
      "classroom_community_bonding": false,
      "thematically_adaptable": false,
      "flashcards": [
        { "term": "accident", "definition": "ulykke" },
        { "term": "adequate", "definition": "tilstrekkelig" },
        { "term": "agriculture", "definition": "landbruk" },
        { "term": "aileron", "definition": "balanseror" },
        { "term": "alteration", "definition": "endring" },
        { "term": "amendment", "definition": "tillegg, endring" },
        { "term": "array", "definition": "rekke, utvalg" },
        { "term": "assembly", "definition": "samling, montering" },
        { "term": "assignment", "definition": "oppgave" },
        { "term": "assurance", "definition": "forsikring, garanti" },
        { "term": "authority", "definition": "myndighet" },
        { "term": "blurred", "definition": "uklart, uskarpt" },
        { "term": "brickie", "definition": "murer" },
        { "term": "building code", "definition": "byggeforskrift" },
        { "term": "bullhorn", "definition": "megafon" },
        { "term": "carrier", "definition": "transportør, flyselskap" },
        { "term": "cause", "definition": "årsak" },
        { "term": "cement mixer", "definition": "sementblander" },
        { "term": "chemical", "definition": "kjemikalie" },
        { "term": "chorus", "definition": "kor" },
        { "term": "concern", "definition": "bekymring" },
        { "term": "condition", "definition": "tilstand" },
        { "term": "confirm", "definition": "bekrefte" },
        { "term": "construction", "definition": "bygg og anlegg" },
        { "term": "cooperation", "definition": "samarbeid" },
        { "term": "council", "definition": "råd, kommune" },
        { "term": "countrywide", "definition": "landsomfattende" },
        { "term": "damage (v)", "definition": "skade" },
        { "term": "disbelief", "definition": "vantro" },
        { "term": "disease", "definition": "sykdom" },
        { "term": "dizzy", "definition": "svimmel" },
        { "term": "doohickey", "definition": "dings, dingsbums" },
        { "term": "dust", "definition": "støv" },
        { "term": "employed", "definition": "ansatt" },
        { "term": "employer", "definition": "arbeidsgiver" },
        { "term": "emergency lights", "definition": "nødlys" },
        { "term": "enforce", "definition": "håndheve" },
        { "term": "ensure", "definition": "sikre, sørge for" },
        { "term": "equipment", "definition": "utstyr" },
        { "term": "ergonomics", "definition": "ergonomi" },
        { "term": "essentially", "definition": "i hovedsak" },
        { "term": "exhausted", "definition": "utmattet" },
        { "term": "extreme", "definition": "ekstrem" },
        { "term": "facilitate", "definition": "lette, tilrettelegge" },
        { "term": "FAA", "definition": "amerikanske luftfartsmyndigheter" },
        { "term": "gasp", "definition": "gispe" },
        { "term": "goggles", "definition": "vernebriller" },
        { "term": "graft (n)", "definition": "slit, hardt arbeid" },
        { "term": "hardhat", "definition": "hjelm" },
        { "term": "hazard", "definition": "fare" },
        { "term": "hod", "definition": "murbøtte" },
        { "term": "HSE", "definition": "HMS" },
        { "term": "include", "definition": "inkludere" },
        { "term": "injury", "definition": "skade" },
        { "term": "integrity", "definition": "integritet, helhet" },
        { "term": "junior executive", "definition": "yngre leder" },
        { "term": "labourer", "definition": "arbeider, hjelpearbeider" },
        { "term": "landline", "definition": "fasttelefon" },
        { "term": "lever", "definition": "spak" },
        { "term": "lumberjack", "definition": "tømmerhogger" },
        { "term": "means of egress", "definition": "rømningsvei" },
        { "term": "minimum", "definition": "minimum" },
        { "term": "mining", "definition": "gruvedrift" },
        { "term": "obvious", "definition": "opplagt" },
        { "term": "parking lot", "definition": "parkeringsplass" },
        { "term": "performance", "definition": "ytelse, prestasjon" },
        { "term": "perception", "definition": "oppfatning" },
        { "term": "power tool", "definition": "elektrisk verktøy" },
        { "term": "precaution", "definition": "forholdsregel" },
        { "term": "prevent", "definition": "forhindre" },
        { "term": "principal", "definition": "rektor" },
        { "term": "procedure", "definition": "prosedyre" },
        { "term": "protective clothing", "definition": "verneklær" },
        { "term": "provision", "definition": "bestemmelse" },
        { "term": "puke (v)", "definition": "kaste opp, spy" },
        { "term": "pulley", "definition": "trinse" },
        { "term": "recovery", "definition": "bedring, restitusjon" },
        { "term": "redundant", "definition": "overflødig" },
        { "term": "related to", "definition": "relatert til" },
        { "term": "relentless", "definition": "ubønnhørlig, nådeløs" },
        { "term": "relevant", "definition": "relevant" },
        { "term": "regulation", "definition": "forskrift, regulering" },
        { "term": "requirement", "definition": "krav" },
        { "term": "respirator", "definition": "åndedrettsvern" },
        { "term": "safety signs", "definition": "sikkerhetsskilt" },
        { "term": "sanitation", "definition": "sanitærforhold" },
        { "term": "scaffold", "definition": "stillas" },
        { "term": "scorching", "definition": "brennhet" },
        { "term": "semi-silence", "definition": "nesten stillhet" },
        { "term": "site agent", "definition": "byggeleder" },
        { "term": "sophisticated", "definition": "sofistikert, avansert" },
        { "term": "stagger", "definition": "sjangle, vakle" },
        { "term": "stainless", "definition": "rustfritt" },
        { "term": "standard", "definition": "standard" },
        { "term": "structural", "definition": "strukturell" },
        { "term": "sturdy", "definition": "solid, robust" },
        { "term": "supervision", "definition": "tilsyn, veiledning" },
        { "term": "tape deck", "definition": "kassettspiller" },
        { "term": "ventilation", "definition": "ventilasjon" },
        { "term": "vibration", "definition": "vibrasjon" },
        { "term": "violate", "definition": "bryte, krenke" },
        { "term": "volatile", "definition": "flyktig, ustabil" },
        { "term": "whistle (n)", "definition": "fløyte, signal" },
        { "term": "workplace culture", "definition": "arbeidsplasskultur" }
      ]
    }
  },
  {
    "title": "Vocabulary Chapter 3: That's Life",
    "full_description": "Flashcards for Chapter 3: That's Life. Click on a card to see the translation.",
    "tags": {
      "main_category": "Skills",
      "sub_category": ["Bygg & Anleggsfag"],
      "cefr_level": ["A2", "B1", "B2"],
      "group_size": ["Individual", "Pairs"],
      "preparation_required": "No Preparation (On-the-spot)",
      "materials_resources": ["Digital Device"],
      "sensitivity_warning": false,
      "activity_type": ["Vocabulary Building", "Self-study", "Flashcards"],
      "classroom_community_bonding": false,
      "thematically_adaptable": false,
      "flashcards": [
        { "term": "acknowledge", "definition": "anerkjenne, innrømme" },
        { "term": "addiction", "definition": "avhengighet" },
        { "term": "affected", "definition": "berørt, påvirket" },
        { "term": "aisle", "definition": "midtgang" },
        { "term": "amusement park", "definition": "fornøyelsespark" },
        { "term": "appalled", "definition": "forferdet" },
        { "term": "appearance", "definition": "utseende" },
        { "term": "apply for", "definition": "søke på" },
        { "term": "approach (v)", "definition": "nærme seg" },
        { "term": "artificial", "definition": "kunstig" },
        { "term": "bagger", "definition": "pakkeperson" },
        { "term": "burden", "definition": "byrde" },
        { "term": "carry on", "definition": "fortsette" },
        { "term": "cause", "definition": "årsak" },
        { "term": "cereal", "definition": "frokostblanding" },
        { "term": "challenge", "definition": "utfordring" },
        { "term": "clear up", "definition": "rydde opp" },
        { "term": "clerk", "definition": "ekspeditør" },
        { "term": "condiment", "definition": "krydder, tilbehør" },
        { "term": "concerned", "definition": "bekymret" },
        { "term": "confront", "definition": "konfrontere" },
        { "term": "consume", "definition": "konsumere, spise" },
        { "term": "content (n)", "definition": "innhold" },
        { "term": "considerable", "definition": "betydelig" },
        { "term": "cotton candy", "definition": "sukkerspinn" },
        { "term": "courage", "definition": "mot" },
        { "term": "credit", "definition": "æren, ros" },
        { "term": "cyberbullying", "definition": "nettmobbing" },
        { "term": "dehydration", "definition": "dehydrering" },
        { "term": "diverse", "definition": "mangfoldig" },
        { "term": "downward", "definition": "nedadgående" },
        { "term": "dropped from the cradle", "definition": "(uttrykk) dum" },
        { "term": "emergency room (ER)", "definition": "akuttmottak" },
        { "term": "emotion", "definition": "følelse" },
        { "term": "escort", "definition": "eskortere" },
        { "term": "exception", "definition": "unntak" },
        { "term": "exposed to", "definition": "utsatt for" },
        { "term": "first impression", "definition": "førsteinntrykk" },
        { "term": "fluid", "definition": "væske" },
        { "term": "foggy", "definition": "tåkete, uklar" },
        { "term": "frizz", "definition": "krusete hår" },
        { "term": "gallon", "definition": "gallon, ca. 3,8 liter" },
        { "term": "get rid of", "definition": "bli kvitt" },
        { "term": "Hoover vacuum", "definition": "Hoover-støvsuger" },
        { "term": "horrified", "definition": "forferdet" },
        { "term": "in public", "definition": "offentlig" },
        { "term": "inch", "definition": "tomme, ca. 2,5 cm" },
        { "term": "incredibly", "definition": "utrolig" },
        { "term": "insult (n)", "definition": "fornærmelse" },
        { "term": "interact", "definition": "samhandle" },
        { "term": "interrogation", "definition": "avhør" },
        { "term": "malfunction", "definition": "funksjonsfeil" },
        { "term": "manner", "definition": "måte" },
        { "term": "moisture", "definition": "fuktighet" },
        { "term": "multiple", "definition": "flere" },
        { "term": "obscenity", "definition": "uanstendighet" },
        { "term": "occasional", "definition": " sporadisk, av og til" },
        { "term": "outcast", "definition": "utstøtt" },
        { "term": "outcome", "definition": "utfall, resultat" },
        { "term": "overwhelmed", "definition": "overveldet" },
        { "term": "paragraph", "definition": "avsnitt" },
        { "term": "pass out", "definition": "besvime" },
        { "term": "pathetic", "definition": "patetisk, ynkelig" },
        { "term": "peak", "definition": "toppunkt" },
        { "term": "pee (n)", "definition": "tiss" },
        { "term": "personality", "definition": "personlighet" },
        { "term": "poison", "definition": "gift" },
        { "term": "pretty solidly", "definition": "ganske solid" },
        { "term": "punch (v)", "definition": "slå" },
        { "term": "raging", "definition": "rasende" },
        { "term": "recent", "definition": "nylig" },
        { "term": "recipe", "definition": "oppskrift" },
        { "term": "relief", "definition": "lettelse" },
        { "term": "research", "definition": "forskning" },
        { "term": "reveal", "definition": "avsløre" },
        { "term": "roller coaster", "definition": "berg-og-dal-bane" },
        { "term": "rubbish", "definition": "søppel, tull" },
        { "term": "scoop (n)", "definition": "øse, scoop" },
        { "term": "self-esteem", "definition": "selvtillit" },
        { "term": "severely", "definition": "alvorlig" },
        { "term": "sheet", "definition": "laken" },
        { "term": "side effect", "definition": "bivirkning" },
        { "term": "significantly", "definition": "betydelig" },
        { "term": "sink", "definition": "vask" },
        { "term": "spice", "definition": "krydder" },
        { "term": "stare", "definition": "stirring" },
        { "term": "starve", "definition": "sulte" },
        { "term": "subject", "definition": "emne, tema" },
        { "term": "survey", "definition": "undersøkelse" },
        { "term": "thus", "definition": "dermed" },
        { "term": "ticking along", "definition": "gå sin gang" },
        { "term": "TMZ", "definition": "kjendisnettsted" },
        { "term": "trash can", "definition": "søppelbøtte" },
        { "term": "vomit (v)", "definition": "kaste opp" },
        { "term": "waist", "definition": "midje" },
        { "term": "weird", "definition": "rar, merkelig" }
      ]
    }
  },
  {
    "title": "Vocabulary Chapter 4: Citizens",
    "full_description": "Flashcards for Chapter 4: Citizens. Click on a card to see the translation.",
    "tags": {
      "main_category": "Skills",
      "sub_category": ["Bygg & Anleggsfag"],
      "cefr_level": ["A2", "B1", "B2"],
      "group_size": ["Individual", "Pairs"],
      "preparation_required": "No Preparation (On-the-spot)",
      "materials_resources": ["Digital Device"],
      "sensitivity_warning": false,
      "activity_type": ["Vocabulary Building", "Self-study", "Flashcards"],
      "classroom_community_bonding": false,
      "thematically_adaptable": false,
      "flashcards": [
        { "term": "abandoned", "definition": "forlatt" },
        { "term": "activism", "definition": "aktivisme" },
        { "term": "activist", "definition": "aktivist" },
        { "term": "align with", "definition": "stille seg på linje med" },
        { "term": "amass", "definition": "samle, hope opp" },
        { "term": "assault", "definition": "overfall, angrep" },
        { "term": "background check", "definition": "bakgrunnssjekk" },
        { "term": "badge", "definition": "merke, skilt" },
        { "term": "bias", "definition": "fordom, skjevhet" },
        { "term": "brights", "definition": "fjernlys" },
        { "term": "buzz cut", "definition": "kortklipt sveis" },
        { "term": "case worker", "definition": "saksbehandler" },
        { "term": "cause", "definition": "sak, formål" },
        { "term": "Census Bureau", "definition": "statistisk sentralbyrå" },
        { "term": "citizen", "definition": "borger" },
        { "term": "civil engagement", "definition": "samfunnsengasjement" },
        { "term": "civil rights", "definition": "borgerrettigheter" },
        { "term": "civil rights movement", "definition": "borgerrettsbevegelsen" },
        { "term": "civilians", "definition": "sivile" },
        { "term": "community", "definition": "samfunn, fellesskap" },
        { "term": "conceive of", "definition": "forestille seg" },
        { "term": "condemnation", "definition": "fordømmelse" },
        { "term": "consequences", "definition": "konsekvenser" },
        { "term": "conspiracy", "definition": "konspirasjon" },
        { "term": "contribute", "definition": "bidra" },
        { "term": "coworker", "definition": "kollega" },
        { "term": "crank", "definition": "sveive, starte" },
        { "term": "cuss", "definition": "banne" },
        { "term": "dawn (n)", "definition": "daggry" },
        { "term": "decade", "definition": "tiår" },
        { "term": "decrease", "definition": "nedgang" },
        { "term": "deduct", "definition": "trekke fra" },
        { "term": "demote", "definition": "degradere" },
        { "term": "dentistry", "definition": "tannlegevitenskap" },
        { "term": "dignitary", "definition": "dignitær, høytstående person" },
        { "term": "disappear", "definition": "forsvinne" },
        { "term": "disclaimer", "definition": "ansvarsfraskrivelse" },
        { "term": "distrustful", "definition": "mistenksom" },
        { "term": "echo chamber", "definition": "ekkokammer" },
        { "term": "elaborate", "definition": "omfattende, detaljert" },
        { "term": "election", "definition": "valg" },
        { "term": "emission", "definition": "utslipp" },
        { "term": "emerge", "definition": "komme til syne, dukke opp" },
        { "term": "empowerment", "definition": "myndiggjøring" },
        { "term": "engage in", "definition": "engasjere seg i" },
        { "term": "ensure", "definition": "sikre, sørge for" },
        { "term": "ethnic minority", "definition": "etnisk minoritet" },
        { "term": "extend an olive branch", "definition": "rekke ut en olivengren" },
        { "term": "fake news", "definition": "falske nyheter" },
        { "term": "fatal", "definition": "dødelig" },
        { "term": "fee", "definition": "avgift, gebyr" },
        { "term": "former", "definition": "tidligere" },
        { "term": "fund (v)", "definition": "finansiere" },
        { "term": "give notice", "definition": "si opp" },
        { "term": "guilty", "definition": "skyldig" },
        { "term": "high-capacity bullet magazine", "definition": "høykapasitetsmagasin" },
        { "term": "hoax", "definition": "bløff, lureri" },
        { "term": "homeless shelter", "definition": "hjemløsherberge" },
        { "term": "horrible", "definition": "forferdelig" },
        { "term": "household", "definition": "husholdning" },
        { "term": "humiliate", "definition": "ydmyke" },
        { "term": "hunch", "definition": "magefølelse, anelse" },
        { "term": "ignition", "definition": "tenning" },
        { "term": "impact", "definition": "innvirkning" },
        { "term": "implement", "definition": "iverksette, implementere" },
        { "term": "impression", "definition": "inntrykk" },
        { "term": "in accordance", "definition": "i henhold til" },
        { "term": "inch", "definition": "tomme" },
        { "term": "incident", "definition": "hendelse" },
        { "term": "income level", "definition": "inntektsnivå" },
        { "term": "increase", "definition": "økning" },
        { "term": "increase (n)", "definition": "økning" },
        { "term": "independent", "definition": "uavhengig" },
        { "term": "indiscernible", "definition": "uutslettelig, utydelig" },
        { "term": "insurance", "definition": "forsikring" },
        { "term": "intentionally", "definition": "med vilje" },
        { "term": "itemized", "definition": "spesifisert" },
        { "term": "jerk (v)", "definition": "rykke" },
        { "term": "landlady", "definition": "vertinne" },
        { "term": "lasting", "definition": "varig" },
        { "term": "law enforcement", "definition": "politivesen" },
        { "term": "license", "definition": "førerkort, lisens" },
        { "term": "listed", "definition": "vernet, listeført" },
        { "term": "manipulation", "definition": "manipulasjon" },
        { "term": "maneuver", "definition": "manøver" },
        { "term": "measure (n)", "definition": "tiltak" },
        { "term": "minimum wage", "definition": "minstelønn" },
        { "term": "MIT", "definition": "amerikansk universitet" },
        { "term": "modified", "definition": "modifisert" },
        { "term": "monitor", "definition": "overvåke" },
        { "term": "narrative", "definition": "fortelling" },
        { "term": "notice", "definition": "oppsigelse" },
        { "term": "offensive", "definition": "støtende" },
        { "term": "opinion", "definition": "mening" },
        { "term": "opposed to", "definition": "i motsetning til" },
        { "term": "past (n)", "definition": "fortid" },
        { "term": "pat down", "definition": "kroppsvisitere" },
        { "term": "pay statement", "definition": "lønnsslipp" },
        { "term": "plantation", "definition": "plantasje" },
        { "term": "plead", "definition": "bønnfalle" },
        { "term": "plesiosaurus", "definition": "svaneøgle" },
        { "term": "poll", "definition": "meningsmåling" },
        { "term": "population", "definition": "befolkning" },
        { "term": "pound (v)", "definition": "banke" },
        { "term": "prejudice", "definition": "fordommer" },
        { "term": "premise (n)", "definition": "premiss, utgangspunkt" },
        { "term": "prestigious", "definition": "prestisjetung" },
        { "term": "prominent", "definition": "fremtredende" },
        { "term": "prominently", "definition": "fremtredende" },
        { "term": "protest", "definition": "protest" },
        { "term": "pseudo-patriotic", "definition": "pseudopatriotisk" },
        { "term": "public outrage", "definition": "offentlig raseri" },
        { "term": "rally", "definition": "demonstrasjon, folkemøte" },
        { "term": "rank (v)", "definition": "rangere" },
        { "term": "reference", "definition": "attest" },
        { "term": "registered nurse", "definition": "offentlig godkjent sykepleier" },
        { "term": "registration", "definition": "vognkort" },
        { "term": "reinforce", "definition": "forsterke" },
        { "term": "released", "definition": "løslatt" },
        { "term": "rerun", "definition": "reprise" },
        { "term": "resident", "definition": "innbygger" },
        { "term": "resistance", "definition": "motstand" },
        { "term": "revenue", "definition": "inntekt" },
        { "term": "ridiculous", "definition": "latterlig" },
        { "term": "rural", "definition": "landlig" },
        { "term": "scholarship", "definition": "stipend" },
        { "term": "senior citizen", "definition": "pensjonist" },
        { "term": "shunned", "definition": "utstøtt, unngått" },
        { "term": "significantly", "definition": "betydelig" },
        { "term": "slogan", "definition": "slagord" },
        { "term": "solitary", "definition": "enslig" },
        { "term": "sprout", "definition": "spire" },
        { "term": "stand at attention", "definition": "stå i rett" },
        { "term": "stepladder", "definition": "gardintrapp" },
        { "term": "stock", "definition": "varelager" },
        { "term": "subsequently", "definition": "deretter, følgelig" },
        { "term": "suburb", "definition": "forstad" },
        { "term": "suffer", "definition": "lide" },
        { "term": "supposedly", "definition": "angivelig" },
        { "term": "survey", "definition": "undersøkelse" },
        { "term": "tail off", "definition": "avta" },
        { "term": "taillight", "definition": "baklys" },
        { "term": "terminate", "definition": "avslutte" },
        { "term": "three quarters", "definition": "tre fjerdedeler" },
        { "term": "trade union", "definition": "fagforening" },
        { "term": "treason", "definition": "forræderi" },
        { "term": "universal", "definition": "universell" },
        { "term": "unsourced", "definition": "uten kilde" },
        { "term": "violate", "definition": "bryte, krenke" },
        { "term": "visible", "definition": "synlig" },
        { "term": "volunteerism", "definition": "frivillig arbeid" },
        { "term": "webcam", "definition": "webkamera" },
        { "term": "withdrawal", "definition": "tilbaketrekning" },
        { "term": "Working Environment Act", "definition": "arbeidsmiljøloven" },
        { "term": "yank (v)", "definition": "rykke" },
        { "term": "zebra crossing", "definition": "fotgjengerovergang" }
      ]
    }
  },
  {
    "title": "Vocabulary Chapter 5: Tools of the Trade",
    "full_description": "Flashcards for Chapter 5: Tools of the Trade. Click on a card to see the translation.",
    "tags": {
      "main_category": "Skills",
      "sub_category": ["Bygg & Anleggsfag"],
      "cefr_level": ["A2", "B1", "B2"],
      "group_size": ["Individual", "Pairs"],
      "preparation_required": "No Preparation (On-the-spot)",
      "materials_resources": ["Digital Device"],
      "sensitivity_warning": false,
      "activity_type": ["Vocabulary Building", "Self-study", "Flashcards"],
      "classroom_community_bonding": false,
      "thematically_adaptable": false,
      "flashcards": [
        { "term": "absorb", "definition": "absorbere" },
        { "term": "accurate", "definition": "nøyaktig" },
        { "term": "additive", "definition": "tilsetningsstoff" },
        { "term": "aerated", "definition": "lufte" },
        { "term": "anneal", "definition": "herde, avspenningsgløde" },
        { "term": "appliances", "definition": "hvitevarer, apparater" },
        { "term": "appearance", "definition": "utseende" },
        { "term": "ash", "definition": "ask" },
        { "term": "assemble", "definition": "montere" },
        { "term": "backfilling", "definition": "tilbakefylling" },
        { "term": "beam", "definition": "bjelke" },
        { "term": "blueprint", "definition": "arbeidstegning" },
        { "term": "board", "definition": "bord, planke" },
        { "term": "bond", "definition": "forband, binding" },
        { "term": "brick", "definition": "murstein" },
        { "term": "bricklayer", "definition": "murer" },
        { "term": "brittle", "definition": "sprøtt" },
        { "term": "carbon footprint", "definition": "karbonavtrykk" },
        { "term": "carpenter", "definition": "snekker, tømrer" },
        { "term": "carpentry", "definition": "tømrerarbeid" },
        { "term": "cedar", "definition": "sedertre" },
        { "term": "cladding", "definition": "kledning" },
        { "term": "clay", "definition": "leire" },
        { "term": "collaboration", "definition": "samarbeid" },
        { "term": "combination spanner", "definition": "fastnøkkel" },
        { "term": "compactor", "definition": "komprimator, platevibrator" },
        { "term": "compass", "definition": "passer" },
        { "term": "component", "definition": "komponent, del" },
        { "term": "compressive strength", "definition": "trykkfasthet" },
        { "term": "concrete", "definition": "betong" },
        { "term": "consistency", "definition": "konsistens" },
        { "term": "consume", "definition": "forbruke" },
        { "term": "coupler", "definition": "kobling" },
        { "term": "creek", "definition": "bekk" },
        { "term": "cross-section drawing", "definition": "snittegning" },
        { "term": "crucial", "definition": "avgjørende" },
        { "term": "cutaway drawing", "definition": "snittegning" },
        { "term": "decking", "definition": "terrassebord" },
        { "term": "demolition", "definition": "riving" },
        { "term": "drainage", "definition": "drenering" },
        { "term": "drawing board", "definition": "tegnebrett" },
        { "term": "durable", "definition": "holdbar" },
        { "term": "efficiently", "definition": "effektivt" },
        { "term": "elevated view drawing", "definition": "fasadetegning" },
        { "term": "endure", "definition": "tåle, holde ut" },
        { "term": "evolve", "definition": "utvikle seg" },
        { "term": "excavator", "definition": "gravemaskin" },
        { "term": "exchange", "definition": "utveksling" },
        { "term": "exploded-view drawing", "definition": "sprengskisse" },
        { "term": "exposure", "definition": "eksponering" },
        { "term": "façade", "definition": "fasade" },
        { "term": "float process", "definition": "floatglassprosess" },
        { "term": "floor plan", "definition": "planløsning" },
        { "term": "flow chart", "definition": "flytskjema" },
        { "term": "fuse", "definition": "smelte sammen" },
        { "term": "gazebo", "definition": "lysthus" },
        { "term": "generate", "definition": "generere, produsere" },
        { "term": "glulam", "definition": "limtre" },
        { "term": "goods", "definition": "varer" },
        { "term": "grading", "definition": "planering" },
        { "term": "grapple", "definition": "klo, griper" },
        { "term": "gravel", "definition": "grus" },
        { "term": "grid", "definition": "rutenett" },
        { "term": "handrails", "definition": "gelender" },
        { "term": "hardware", "definition": "jernvarer" },
        { "term": "hardwood", "definition": "hardt trevirke" },
        { "term": "harvesting", "definition": "hogst, innhøsting" },
        { "term": "herb", "definition": "urt" },
        { "term": "hexagonal spanner", "definition": "sekskantnøkkel" },
        { "term": "hoe", "definition": "hakke" },
        { "term": "hoist", "definition": "heise" },
        { "term": "inhabitant", "definition": "innbygger" },
        { "term": "irrigation", "definition": "vanning" },
        { "term": "jackhammer", "definition": "trykkluftbor" },
        { "term": "jaw", "definition": "kjeve" },
        { "term": "journeyman's certificate", "definition": "svennebrev" },
        { "term": "landscaping", "definition": "anleggsgartnerarbeid" },
        { "term": "layer", "definition": "lag" },
        { "term": "levee", "definition": "elvevoll" },
        { "term": "levelling tool", "definition": "vater" },
        { "term": "light fixture", "definition": "belysning, lampe" },
        { "term": "lime", "definition": "kalk" },
        { "term": "limestone", "definition": "kalkstein" },
        { "term": "loader", "definition": "laster" },
        { "term": "log", "definition": "tømmerstokk" },
        { "term": "loppers", "definition": "grensaks" },
        { "term": "lumber", "definition": "tømmer" },
        { "term": "maintenance", "definition": "vedlikehold" },
        { "term": "mark-out", "definition": "oppmerking" },
        { "term": "masonry", "definition": "murverk" },
        { "term": "measurement", "definition": "mål" },
        { "term": "medieval", "definition": "middelaldersk" },
        { "term": "meticulous", "definition": "nøye, grundig" },
        { "term": "mini-excavator", "definition": "minigraver" },
        { "term": "molten", "definition": "smeltet" },
        { "term": "mortar", "definition": "mørtel" },
        { "term": "mould", "definition": "støpeform" },
        { "term": "mould (v)", "definition": "støpe" },
        { "term": "moulding", "definition": "listverk" },
        { "term": "mow", "definition": "klippe gress" },
        { "term": "nibbler", "definition": "platesaks" },
        { "term": "non-toxic", "definition": "giftfri" },
        { "term": "off site", "definition": "utenfor byggeplassen" },
        { "term": "pattern", "definition": "mønster" },
        { "term": "pavement", "definition": "fortau" },
        { "term": "pile", "definition": "haug, stabel" },
        { "term": "pile driver", "definition": "peledriver" },
        { "term": "pine", "definition": "furu" },
        { "term": "plaster", "definition": "puss, gips" },
        { "term": "pliers", "definition": "tang" },
        { "term": "population", "definition": "befolkning" },
        { "term": "protractor", "definition": "gradskive" },
        { "term": "pry bar", "definition": "brekkjern" },
        { "term": "purpose", "definition": "formål" },
        { "term": "ratchet spanner", "definition": "skrallenøkkel" },
        { "term": "reinforce", "definition": "forsterke" },
        { "term": "renewable", "definition": "fornybar" },
        { "term": "renovation", "definition": "renovering" },
        { "term": "resin", "definition": "harpiks, resin" },
        { "term": "retaining wall", "definition": "støttemur" },
        { "term": "rift", "definition": "sprekk, kløft" },
        { "term": "riveter", "definition": "nagler" },
        { "term": "rock blaster", "definition": "fjellsprenger" },
        { "term": "rock blasting", "definition": "fjellsprengning" },
        { "term": "rod", "definition": "stang" },
        { "term": "roofer", "definition": "taktekker" },
        { "term": "safety harness", "definition": "sikkerhetssele" },
        { "term": "scaffolder", "definition": "stillasbygger" },
        { "term": "scaffolding", "definition": "stillas" },
        { "term": "seam roofing machinery", "definition": "falsemaskin" },
        { "term": "secateurs", "definition": "beskjæringssaks" },
        { "term": "self-explanatory", "definition": "selvforklarende" },
        { "term": "service life", "definition": "levetid" },
        { "term": "shade", "definition": "skygge" },
        { "term": "shears", "definition": "saks" },
        { "term": "shrub", "definition": "busk" },
        { "term": "slate", "definition": "skifer" },
        { "term": "sloping", "definition": "skrånende" },
        { "term": "soil", "definition": "jord" },
        { "term": "soldering", "definition": "lodding" },
        { "term": "solution", "definition": "løsning" },
        { "term": "source", "definition": "kilde" },
        { "term": "species", "definition": "art, treslag" },
        { "term": "specification drawing", "definition": "spesifikasjonstegning" },
        { "term": "spite", "definition": "tross, ondskap" },
        { "term": "spruce", "definition": "gran" },
        { "term": "stained glass", "definition": "glassmaleri" },
        { "term": "supplies", "definition": "rekvisita, forsyninger" },
        { "term": "surface", "definition": "overflate" },
        { "term": "sustainable", "definition": "bærekraftig" },
        { "term": "T-square", "definition": "T-linjal" },
        { "term": "tensile strength", "definition": "strekkfasthet" },
        { "term": "term", "definition": "begrep" },
        { "term": "tiling", "definition": "flislegging" },
        { "term": "time consuming", "definition": "tidkrevende" },
        { "term": "tinsmith", "definition": "blikkenslager" },
        { "term": "trade (v)", "definition": "bytte" },
        { "term": "treat", "definition": "behandle" },
        { "term": "trench", "definition": "grøft" },
        { "term": "urban", "definition": "urban, by-" },
        { "term": "vegetation", "definition": "vegetasjon, planteliv" },
        { "term": "walkway", "definition": "gangsti" },
        { "term": "waste", "definition": "avfall" },
        { "term": "water feature", "definition": "vannelement" },
        { "term": "without a hitch", "definition": "uten problemer" },
        { "term": "wood products carpenter", "definition": "trevaresnekker" }
      ]
    }
  },
  {
    "title": "Vocabulary Chapter 6: Solutions",
    "full_description": "Flashcards for Chapter 6: Solutions. Click on a card to see the translation.",
    "tags": {
      "main_category": "Skills",
      "sub_category": ["Bygg & Anleggsfag"],
      "cefr_level": ["A2", "B1", "B2"],
      "group_size": ["Individual", "Pairs"],
      "preparation_required": "No Preparation (On-the-spot)",
      "materials_resources": ["Digital Device"],
      "sensitivity_warning": false,
      "activity_type": ["Vocabulary Building", "Self-study", "Flashcards"],
      "classroom_community_bonding": false,
      "thematically_adaptable": false,
      "flashcards": [
        { "term": "accomplishment", "definition": "prestasjon" },
        { "term": "adolescent", "definition": "ungdom" },
        { "term": "adapt to", "definition": "tilpasse seg" },
        { "term": "annual", "definition": "årlig" },
        { "term": "assault", "definition": "overfall, angrep" },
        { "term": "bedside table", "definition": "nattbord" },
        { "term": "call-out", "definition": "utrykning, vaktutkalling" },
        { "term": "capability", "definition": "kapasitet, evne" },
        { "term": "communication skills", "definition": "kommunikasjonsevner" },
        { "term": "compassion", "definition": "medfølelse" },
        { "term": "consciousness", "definition": "bevissthet" },
        { "term": "contraption", "definition": "innretning, dings" },
        { "term": "crew cut", "definition": "kortklipt sveis" },
        { "term": "deported", "definition": "deportert" },
        { "term": "digest", "definition": "fordøye" },
        { "term": "disgrace", "definition": "skam" },
        { "term": "displace", "definition": "fortrenge, erstatte" },
        { "term": "evolve", "definition": "utvikle seg" },
        { "term": "fire brigade", "definition": "brannvesen" },
        { "term": "fumble", "definition": "famle" },
        { "term": "fuse", "definition": "smelte sammen" },
        { "term": "garishly", "definition": "prangende" },
        { "term": "GDP", "definition": "BNP - bruttonasjonalprodukt" },
        { "term": "glue", "definition": "lim" },
        { "term": "gruff", "definition": "barsk, brysk" },
        { "term": "hazy", "definition": "uklar, disig" },
        { "term": "independent", "definition": "selvstendig" },
        { "term": "index of refraction", "definition": "brytningsindeks" },
        { "term": "inequality", "definition": "ulikhet" },
        { "term": "infinite", "definition": "uendelig" },
        { "term": "innovation", "definition": "innovasjon" },
        { "term": "infrastructure", "definition": "infrastruktur" },
        { "term": "leakage", "definition": "lekkasje" },
        { "term": "maintenance", "definition": "vedlikehold" },
        { "term": "maintenance contract", "definition": "serviceavtale" },
        { "term": "manufacturing job", "definition": "industrijobb" },
        { "term": "merge", "definition": "slå sammen" },
        { "term": "Mexican mullet", "definition": "hockeysveis" },
        { "term": "neurosurgeon", "definition": "nevrokirurg" },
        { "term": "participate", "definition": "delta" },
        { "term": "plywood", "definition": "kryssfiner" },
        { "term": "policymaker", "definition": "politiker" },
        { "term": "poverty line", "definition": "fattigdomsgrense" },
        { "term": "precious", "definition": "dyrebar" },
        { "term": "presence", "definition": "nærvær" },
        { "term": "pressure", "definition": "trykk" },
        { "term": "professional", "definition": "profesjonell" },
        { "term": "publicly traded", "definition": "børsnotert" },
        { "term": "random", "definition": "tilfeldig" },
        { "term": "recall", "definition": "huske" },
        { "term": "recommission", "definition": "sette i drift igjen" },
        { "term": "refrigerant", "definition": "kjølemiddel" },
        { "term": "refrigeration technician", "definition": "kjøletekniker" },
        { "term": "Remotely Operated Vehicle (ROV)", "definition": "fjernstyrt undervannsfarkost" },
        { "term": "replace", "definition": "erstatte" },
        { "term": "rivalry", "definition": "rivalisering" },
        { "term": "self-employed", "definition": "selvstendig næringsdrivende" },
        { "term": "sensation", "definition": "følelse, fornemmelse" },
        { "term": "service truck", "definition": "servicebil" },
        { "term": "service-minded", "definition": "serviceinnstilt" },
        { "term": "shoal", "definition": "stim" },
        { "term": "shimmer", "definition": "skimre" },
        { "term": "sigh", "definition": "sukk" },
        { "term": "soundless", "definition": "lydløs" },
        { "term": "speed limit", "definition": "fartsgrense" },
        { "term": "swagger", "definition": "storbeint gange" },
        { "term": "teamwork", "definition": "lagarbeid" },
        { "term": "technical operations manager", "definition": "teknisk driftsleder" },
        { "term": "tightness", "definition": "tetthet" },
        { "term": "tingle", "definition": "prikke, kile" },
        { "term": "vulnerable", "definition": "sårbar" },
        { "term": "wipe out", "definition": "utslette" }
      ]
    }
  },
  {
    "title": "Vocabulary Chapter 7: Encounters",
    "full_description": "Flashcards for Chapter 7: Encounters. Click on a card to see the translation.",
    "tags": {
      "main_category": "Skills",
      "sub_category": ["Bygg & Anleggsfag"],
      "cefr_level": ["A2", "B1", "B2"],
      "group_size": ["Individual", "Pairs"],
      "preparation_required": "No Preparation (On-the-spot)",
      "materials_resources": ["Digital Device"],
      "sensitivity_warning": false,
      "activity_type": ["Vocabulary Building", "Self-study", "Flashcards"],
      "classroom_community_bonding": false,
      "thematically_adaptable": false,
      "flashcards": [
        { "term": "abominable", "definition": "avskyelig" },
        { "term": "across borders", "definition": "på tvers av grenser" },
        { "term": "acknowledge", "definition": "anerkjenne" },
        { "term": "ancestral", "definition": "nedarvet" },
        { "term": "aspect", "definition": "aspekt, side" },
        { "term": "assumption", "definition": "antagelse" },
        { "term": "awareness", "definition": "bevissthet" },
        { "term": "battle", "definition": "kamp" },
        { "term": "be obliged to", "definition": "være nødt til" },
        { "term": "bellow (v)", "definition": "brøle" },
        { "term": "blend (v)", "definition": "blande" },
        { "term": "border (n)", "definition": "grense" },
        { "term": "bra", "definition": "BH" },
        { "term": "bunch (v)", "definition": "samle sammen" },
        { "term": "burst (n)", "definition": "utbrudd" },
        { "term": "canvas", "definition": "lerret" },
        { "term": "canvas (n)", "definition": "lerret" },
        { "term": "cause (n)", "definition": "sak, formål" },
        { "term": "character", "definition": "karakter, person" },
        { "term": "charcoal", "definition": "kull" },
        { "term": "chest", "definition": "bryst" },
        { "term": "chin-chin", "definition": "(Nigeriansk snacks)" },
        { "term": "clench (v)", "definition": "knytte" },
        { "term": "clutch (v)", "definition": "gripe" },
        { "term": "comb (v)", "definition": "gre" },
        { "term": "combat (v)", "definition": "bekjempe" },
        { "term": "commentary", "definition": "kommentar" },
        { "term": "concept", "definition": "konsept, begrep" },
        { "term": "consider", "definition": "vurdere" },
        { "term": "couch", "definition": "sofa" },
        { "term": "crease (n)", "definition": "brett, fold" },
        { "term": "cross-cultural", "definition": "tverrkulturell" },
        { "term": "cultural identity", "definition": "kulturell identitet" },
        { "term": "custom", "definition": "skikk" },
        { "term": "debris", "definition": "rester, vrakrester" },
        { "term": "determined", "definition": "bestemt" },
        { "term": "disappointment", "definition": "skuffelse" },
        { "term": "diversity", "definition": "mangfold" },
        { "term": "doodle (v)", "definition": "drodle, tegne" },
        { "term": "drawl (v)", "definition": "snakke slepende" },
        { "term": "elaborate (adj)", "definition": "omfattende, detaljert" },
        { "term": "enclosed", "definition": "vedlagt" },
        { "term": "encounter (n)", "definition": "møte" },
        { "term": "exhibition", "definition": "utstilling" },
        { "term": "explanatory", "definition": "forklarende" },
        { "term": "exposed", "definition": "utsatt, blottlagt" },
        { "term": "facial expression", "definition": "ansiktsuttrykk" },
        { "term": "feature (n)", "definition": "trekk, egenskap" },
        { "term": "folder", "definition": "mappe" },
        { "term": "foreigner", "definition": "utlending" },
        { "term": "forward (n)", "definition": "løper, spiss" },
        { "term": "frenetic", "definition": "hektisk" },
        { "term": "gable", "definition": "gavl" },
        { "term": "generous", "definition": "generøs" },
        { "term": "gesture (n)", "definition": "gest, håndbevegelse" },
        { "term": "gleam (v)", "definition": "glimte" },
        { "term": "glove", "definition": "hanske" },
        { "term": "glove compartment", "definition": "hanskerom" },
        { "term": "glue (n)", "definition": "lim" },
        { "term": "ground (v)", "definition": "male, knuse" },
        { "term": "habit", "definition": "vane" },
        { "term": "hand-out", "definition": "almisse" },
        { "term": "haunches", "definition": "bakpart" },
        { "term": "index finger", "definition": "pekefinger" },
        { "term": "individual", "definition": "individ" },
        { "term": "inequality", "definition": "ulikhet" },
        { "term": "injustice", "definition": "urettferdighet" },
        { "term": "insult (v)", "definition": "fornærme" },
        { "term": "interpret", "definition": "tolke" },
        { "term": "issue (n)", "definition": "sak, problem" },
        { "term": "labour", "definition": "arbeid" },
        { "term": "lace (n)", "definition": "blonde, lisse" },
        { "term": "leaf through", "definition": "bla gjennom" },
        { "term": "lineage", "definition": "slektslinje" },
        { "term": "maple", "definition": "lønn" },
        { "term": "moan (v)", "definition": "stønne" },
        { "term": "moistness", "definition": "fuktighet" },
        { "term": "motionless", "definition": "urørlig" },
        { "term": "moth", "definition": "møll" },
        { "term": "mural", "definition": "veggmaleri" },
        { "term": "nod (v)", "definition": "nikke" },
        { "term": "non-verbal", "definition": "ikke-verbal" },
        { "term": "obvious", "definition": "opplagt" },
        { "term": "order form", "definition": "bestillingsskjema" },
        { "term": "paper plate", "definition": "pappasjett" },
        { "term": "paramilitary", "definition": "paramilitær" },
        { "term": "peer (v)", "definition": "kikke, myse" },
        { "term": "penalty", "definition": "straff" },
        { "term": "persecution", "definition": "forfølgelse" },
        { "term": "petrol drums", "definition": "bensinfat" },
        { "term": "plot", "definition": "handling" },
        { "term": "point of view", "definition": "synsvinkel" },
        { "term": "precise hand", "definition": "nøyaktig hånd" },
        { "term": "prejudiced", "definition": "fordomsfull" },
        { "term": "promote", "definition": "fremme" },
        { "term": "promiscuous", "definition": "promiskuøs" },
        { "term": "protagonist", "definition": "hovedperson" },
        { "term": "rapt", "definition": "henrykt" },
        { "term": "rear-view mirror", "definition": "bakspeil" },
        { "term": "recite", "definition": "resitere, si frem" },
        { "term": "referee", "definition": "dommer" },
        { "term": "relieved", "definition": "lettet" },
        { "term": "restorer", "definition": "restaurerer" },
        { "term": "revitalize", "definition": "revitalisere" },
        { "term": "rink", "definition": "isbane" },
        { "term": "sense (n)", "definition": "fornuft, sans" },
        { "term": "setting", "definition": "setting, miljø" },
        { "term": "settlement", "definition": "bosetning" },
        { "term": "sheathe", "definition": "dekke, hylle" },
        { "term": "shove (v)", "definition": "dytte" },
        { "term": "shuffle (v)", "definition": "subbe" },
        { "term": "skating rink", "definition": "skøytebane" },
        { "term": "sleeve", "definition": "erme" },
        { "term": "smooth (v)", "definition": "glatte ut" },
        { "term": "sorrow", "definition": "sorg" },
        { "term": "startling", "definition": "oppsiktsvekkende" },
        { "term": "stereotype", "definition": "stereotypi" },
        { "term": "stick", "definition": "kølle" },
        { "term": "striking (adj)", "definition": "slående" },
        { "term": "syllable", "definition": "stavelse" },
        { "term": "tear (n)", "definition": "flenge, rift" },
        { "term": "tender", "definition": "øm" },
        { "term": "territorial", "definition": "territoriell" },
        { "term": "theme", "definition": "tema" },
        { "term": "thyme", "definition": "timian" },
        { "term": "trace (v)", "definition": "spore" },
        { "term": "trade (n)", "definition": "handel" },
        { "term": "tranquility", "definition": "ro, stillhet" },
        { "term": "trounce", "definition": "knuse, slå" },
        { "term": "unhook", "definition": "hekte av" },
        { "term": "urgent", "definition": "presserende, haster" },
        { "term": "values", "definition": "verdier" },
        { "term": "vicar", "definition": "sogneprest" },
        { "term": "wrapping", "definition": "innpakning" }
      ]
    }
  },
  {
    "title": "Vocabulary Chapter 8: Perspectives",
    "full_description": "Flashcards for Chapter 8: Perspectives. Click on a card to see the translation.",
    "tags": {
      "main_category": "Skills",
      "sub_category": ["Bygg & Anleggsfag"],
      "cefr_level": ["A2", "B1", "B2"],
      "group_size": ["Individual", "Pairs"],
      "preparation_required": "No Preparation (On-the-spot)",
      "materials_resources": ["Digital Device"],
      "sensitivity_warning": false,
      "activity_type": ["Vocabulary Building", "Self-study", "Flashcards"],
      "classroom_community_bonding": false,
      "thematically_adaptable": false,
      "flashcards": [
        { "term": "access", "definition": "tilgang" },
        { "term": "aesthetic", "definition": "estetisk" },
        { "term": "alert (adj)", "definition": "årvåken, våken" },
        { "term": "anomaly", "definition": "anomali, avvik" },
        { "term": "anthem", "definition": "nasjonalsang" },
        { "term": "aptitude test", "definition": "evnetest" },
        { "term": "archaic", "definition": "arkaisk, gammeldags" },
        { "term": "asylum seeker", "definition": "asylsøker" },
        { "term": "back and forth", "definition": "frem og tilbake" },
        { "term": "barrel", "definition": "tønne, løp" },
        { "term": "be well versed", "definition": "være vel bevandret i" },
        { "term": "belly", "definition": "mage" },
        { "term": "bereaved", "definition": "sørgende" },
        { "term": "biodegrade", "definition": "brytes ned biologisk" },
        { "term": "biodiversity", "definition": "biologisk mangfold" },
        { "term": "blazer", "definition": "blazer, jakke" },
        { "term": "border", "definition": "grense" },
        { "term": "boundary", "definition": "grense" },
        { "term": "bridge (v)", "definition": "bygge bro" },
        { "term": "bully (v)", "definition": "mobbe" },
        { "term": "bursary", "definition": "stipend" },
        { "term": "censor", "definition": "sensurere" },
        { "term": "challenge (v)", "definition": "utfordre" },
        { "term": "chameleon", "definition": "kameleon" },
        { "term": "champion (v)", "definition": "kjempe for" },
        { "term": "chop", "definition": "hugge, kutte" },
        { "term": "civil war", "definition": "borgerkrig" },
        { "term": "claim (v)", "definition": "kreve" },
        { "term": "coastal region", "definition": "kystregion" },
        { "term": "coin a term", "definition": "skape et begrep" },
        { "term": "confetti", "definition": "konfetti" },
        { "term": "consider", "definition": "vurdere" },
        { "term": "constituent", "definition": "bestanddel" },
        { "term": "consume", "definition": "konsumere, forbruke" },
        { "term": "coverage", "definition": "dekning" },
        { "term": "crucial", "definition": "avgjørende" },
        { "term": "cruelty", "definition": "grusomhet" },
        { "term": "crush (n)", "definition": "forelskelse" },
        { "term": "damp", "definition": "fuktig" },
        { "term": "decolonization", "definition": "avkolonisering" },
        { "term": "decline", "definition": "nedgang" },
        { "term": "degrade", "definition": "forringe" },
        { "term": "denial", "definition": "fornektelse" },
        { "term": "denier", "definition": "fornekter" },
        { "term": "designation", "definition": "betegnelse" },
        { "term": "desirable", "definition": "ønskelig" },
        { "term": "despair", "definition": "fortvilelse" },
        { "term": "developing region", "definition": "utviklingsregion" },
        { "term": "dizzy", "definition": "svimmel" },
        { "term": "domestic violence", "definition": "vold i hjemmet" },
        { "term": "downside", "definition": "ulempe" },
        { "term": "durability", "definition": "holdbarhet" },
        { "term": "eardrum", "definition": "trommehinne" },
        { "term": "enshrine", "definition": "nedfelle, stadfeste" },
        { "term": "estimate (n)", "definition": "anslag" },
        { "term": "existential anxiety", "definition": "eksistensiell angst" },
        { "term": "fence", "definition": "gjerde" },
        { "term": "fine-mesh", "definition": "finmasket" },
        { "term": "fixed", "definition": "fast" },
        { "term": "flawed", "definition": "mangelfull" },
        { "term": "flourish", "definition": "blomstre" },
        { "term": "forensic chemist", "definition": "rettskjemiker" },
        { "term": "foundation", "definition": "grunnlag" },
        { "term": "fundamental right", "definition": "grunnleggende rettighet" },
        { "term": "gap (n)", "definition": "gap, kløft" },
        { "term": "gender equality", "definition": "likestilling" },
        { "term": "genital mutilation", "definition": "kjønnslemlestelse" },
        { "term": "genuinely", "definition": "oppriktig" },
        { "term": "give a leg up", "definition": "gi en hjelpende hånd" },
        { "term": "graduate (v)", "definition": "uteksamineres" },
        { "term": "gut (n)", "definition": "tarm" },
        { "term": "high tide line", "definition": "flomål" },
        { "term": "high-rise", "definition": "høyhus" },
        { "term": "homeland", "definition": "hjemland" },
        { "term": "honour society", "definition": "æressamfunn" },
        { "term": "ignorance", "definition": "uvitenhet" },
        { "term": "impact", "definition": "innvirkning" },
        { "term": "impact (v)", "definition": "påvirke" },
        { "term": "in the dock", "definition": "på tiltalebenken" },
        { "term": "indignity", "definition": "ydmykelse" },
        { "term": "irretrievable", "definition": "uopprettelig" },
        { "term": "irrespective", "definition": "uavhengig av" },
        { "term": "justice", "definition": "rettferdighet" },
        { "term": "lenient", "definition": "mild, overbærende" },
        { "term": "limb", "definition": "lem" },
        { "term": "limpet", "definition": "albueskjell" },
        { "term": "literacy", "definition": "lese- og skriveferdighet" },
        { "term": "looming", "definition": "truende" },
        { "term": "malleability", "definition": "formbarhet" },
        { "term": "malnutrition", "definition": "underernæring" },
        { "term": "maroon", "definition": "burgunder" },
        { "term": "mass", "definition": "messe" },
        { "term": "mastah (master)", "definition": "mester" },
        { "term": "melting pot", "definition": "smeltedigel" },
        { "term": "merely", "definition": "bare" },
        { "term": "microplastics", "definition": "mikroplast" },
        { "term": "migrate", "definition": "migrere, flytte" },
        { "term": "mindset", "definition": "tankesett" },
        { "term": "minor", "definition": "mindreårig" },
        { "term": "misbehavior", "definition": "dårlig oppførsel" },
        { "term": "mixed", "definition": "blandet" },
        { "term": "modify", "definition": "modifisere, endre" },
        { "term": "mug (v)", "definition": "rane" },
        { "term": "nourish", "definition": "gi næring" },
        { "term": "number-plate", "definition": "nummerskilt" },
        { "term": "nun", "definition": "nonne" },
        { "term": "oppressor", "definition": "undertrykker" },
        { "term": "patch up", "definition": "lappe sammen" },
        { "term": "pattern", "definition": "mønster" },
        { "term": "perforate", "definition": "perforere, stikke hull på" },
        { "term": "perk", "definition": "fordel" },
        { "term": "perception", "definition": "oppfatning" },
        { "term": "Ph.D.", "definition": "doktorgrad" },
        { "term": "pick a side", "definition": "velge side" },
        { "term": "pity (v)", "definition": "synes synd på" },
        { "term": "plastic-wrapped", "definition": "innpakket i plast" },
        { "term": "pour", "definition": "helle" },
        { "term": "poverty line", "definition": "fattigdomsgrense" },
        { "term": "pride", "definition": "stolthet" },
        { "term": "pristine", "definition": "uberørt" },
        { "term": "progress", "definition": "fremgang" },
        { "term": "property", "definition": "egenskap" },
        { "term": "prosperous", "definition": "velstående" },
        { "term": "prosperity", "definition": "velstand" },
        { "term": "recess", "definition": "friminutt" },
        { "term": "reel (v)", "definition": "sjangale, vakle" },
        { "term": "refugees", "definition": "flyktninger" },
        { "term": "rod", "definition": "stang, kjepp" },
        { "term": "rubble", "definition": "ruiner, murrester" },
        { "term": "rural", "definition": "landlig" },
        { "term": "savage (adj)", "definition": "vill, brutal" },
        { "term": "scholarship", "definition": "stipend" },
        { "term": "segregation", "definition": "segregering, raseskille" },
        { "term": "selfishness", "definition": "egoisme" },
        { "term": "separation", "definition": "atskillelse" },
        { "term": "servitude", "definition": "trelldom" },
        { "term": "shelter", "definition": "ly, tilfluktssted" },
        { "term": "shift (n)", "definition": "skifte, endring" },
        { "term": "shrug", "definition": "trekke på skuldrene" },
        { "term": "sink", "definition": "synke" },
        { "term": "slacks", "definition": "bukser" },
        { "term": "smattering", "definition": "liten mengde" },
        { "term": "species", "definition": "art" },
        { "term": "staggering", "definition": "svimlende" },
        { "term": "stern", "definition": "streng" },
        { "term": "stocked", "definition": "fylt opp" },
        { "term": "stomach", "definition": "mage" },
        { "term": "strip search", "definition": "kroppsvisitering" },
        { "term": "stun", "definition": "overvelde, sjokkere" },
        { "term": "supervision", "definition": "tilsyn" },
        { "term": "survival", "definition": "overlevelse" },
        { "term": "sustainable development", "definition": "bærekraftig utvikling" },
        { "term": "switch over", "definition": "bytte over" },
        { "term": "tap (n)", "definition": "spring, tapp" },
        { "term": "tease (v)", "definition": "erte" },
        { "term": "tender", "definition": "øm" },
        { "term": "tin factory", "definition": "hermetikkfabrikk" },
        { "term": "township", "definition": "township, bydel" },
        { "term": "trafficking", "definition": "menneskehandel" },
        { "term": "underprivileged", "definition": "vanskeligstilt" },
        { "term": "undoubtedly", "definition": "utvilsomt" },
        { "term": "value (n)", "definition": "verdi" },
        { "term": "versatile", "definition": "allsidig" },
        { "term": "vicious", "definition": "ondskapsfull" },
        { "term": "vigilance", "definition": "årvåkenhet" },
        { "term": "war-torn", "definition": "krigsherjet" },
        { "term": "waste", "definition": "avfall" },
        { "term": "well off", "definition": "velstående" },
        { "term": "whip out", "definition": "dra frem raskt" }
      ]
    }
  }
]
